git_sign_off/Git.py
git_sign_off/Process.py
git_sign_off/__init__.py
git_sign_off/__main__.py
git_sign_off/exceptions.py
git_sign_off/sign_off.py
git_sign_off/utils.py
git_sign_off-0.0.0.dist-info/METADATA
git_sign_off-0.0.0.dist-info/WHEEL
git_sign_off-0.0.0.dist-info/entry_points.txt
git_sign_off-0.0.0.dist-info/top_level.txt
git_sign_off-0.0.0.dist-info/RECORD
