Metadata-Version: 2.1
Name: git-sign-off
Version: 0.0.0
Summary: Sign off git certificates for tasks and check them.
Home-page: https://github.com/AlbertoEAF/git-sign-off
Author: Alberto Ferreira
Author-email: AlbertoEAF@users.noreply.github.com
License: MIT
Platform: UNKNOWN
Classifier: License :: OSI Approved :: MIT License
Classifier: Programming Language :: Python :: 3
Classifier: Programming Language :: Python :: 3.6
Requires-Python: >=3.6
